chatbotweb/__init__.py
chatbotweb/chat_server.py
chatbotweb-0.2.7.dist-info/LICENSE
chatbotweb-0.2.7.dist-info/METADATA
chatbotweb-0.2.7.dist-info/WHEEL
chatbotweb-0.2.7.dist-info/top_level.txt
chatbotweb-0.2.7.dist-info/RECORD
