Metadata-Version: 2.1
Name: chatbotweb
Version: 0.2.7
Summary: Automatic generation of web interface for user-defined chatbot
Home-page: UNKNOWN
Author: Yoshiki Ohira
Author-email: ohira.yoshiki@irl.sys.es.osaka-u.ac.jp
License: UNKNOWN
Platform: UNKNOWN
Classifier: Programming Language :: Python :: 3
Classifier: License :: OSI Approved :: BSD License
Classifier: Operating System :: OS Independent
License-File: LICENSE
